lasprs-0.6.1.dist-info/METADATA
lasprs-0.6.1.dist-info/WHEEL
lasprs.libs/libasound-962ca764.so.2
lasprs/filter/__init__.py
lasprs/__init__.py
lasprs/_lasprs.cpython-310-x86_64-linux-gnu.so
lasprs-0.6.1.dist-info/RECORD
