Metadata-Version: 2.3
Name: lasprs
Version: 0.6.1
Classifier: Programming Language :: Rust
Classifier: Programming Language :: Python :: Implementation :: CPython
Classifier: Programming Language :: Python :: Implementation :: PyPy
Requires-Dist: numpy
Summary: Library for Acoustic Signal Processing (Rust edition, with optional Python bindings via pyo3)
Keywords: dsp,audio,measurement,acoustics,filter
Author: J.A. de Jong <j.a.dejong@ascee.nl>
Author-email: J.A. de Jong <j.a.dejong@ascee.nl>
License: MIT OR Apache-2.0
Requires-Python: >=3.7
Project-URL: Source Code, https://code.ascee.nl/ascee/lasprs
